s3_loader/__init__.py
s3_loader/main.py
s3_loader-1.1.6.dist-info/entry_points.txt
s3_loader-1.1.6.dist-info/WHEEL
s3_loader-1.1.6.dist-info/METADATA
s3_loader-1.1.6.dist-info/RECORD
