Metadata-Version: 2.1
Name: s3-loader
Version: 1.1.6
Summary: wrapper script for uploading files and dirs to s3
Home-page: https://github.com/phil-bell/s3-loader
License: GNU General Public License
Author: phil-bell
Author-email: philhabell@gmail.com
Requires-Python: >=3.6.12,<4.0.0
Classifier: License :: Other/Proprietary License
Classifier: Programming Language :: Python :: 3
Classifier: Programming Language :: Python :: 3.7
Classifier: Programming Language :: Python :: 3.8
Classifier: Programming Language :: Python :: 3.9
Requires-Dist: boto3 (>=1.16.63,<2.0.0)
Requires-Dist: python-magic (>=0.4.20,<0.5.0)
Requires-Dist: typer (>=0.3.2,<0.4.0)
Project-URL: Documentation, https://github.com/phil-bell/s3-loader/blob/main/README.md
Project-URL: Repository, https://github.com/phil-bell/s3-loader
